feature_flags/__init__.py
feature_flags/client.py
feature_flags/context_managers.py
feature_flags/decorators.py
feature_flags/exceptions.py
feature_flags/types.py
feature_flag_python-0.1.1.dist-info/METADATA
feature_flag_python-0.1.1.dist-info/WHEEL
feature_flag_python-0.1.1.dist-info/licenses/LICENSE
feature_flag_python-0.1.1.dist-info/RECORD
